kmrpp/__init__.py
kmrpp/__main__.py
kmrpp/core/__init__.py
kmrpp/core/consts.py
kmrpp/core/exceptions.py
kmrpp/core/http.py
kmrpp/core/models.py
kmrpp/core/parse.py
kmrpp-0.1.6.dist-info/LICENSE
kmrpp-0.1.6.dist-info/METADATA
kmrpp-0.1.6.dist-info/WHEEL
kmrpp-0.1.6.dist-info/entry_points.txt
kmrpp-0.1.6.dist-info/top_level.txt
kmrpp-0.1.6.dist-info/RECORD
