Metadata-Version: 2.1
Name: kmrpp
Version: 0.1.6
Summary: (unofficial) cli tool to use parent portal in the terminal
Home-page: https://github.com/st22209/Parent-Portal
Author: FusionSid
Author-email: st22209@ormiston.school.nz
License: UNKNOWN
Platform: UNKNOWN
License-File: LICENSE
Requires-Dist: pydantic (==1.10.2)
Requires-Dist: python-dotenv (==0.21.1)
Requires-Dist: requests (==2.27.1)
Requires-Dist: rich (==13.3.1)
Requires-Dist: setuptools (==58.1.0)
Requires-Dist: typer (==0.7.0)
